{"event":"DEV_MODE","properties":{"app_extensions":[{"version":"3.17.4","group_id":"io.quarkus","artifact_id":"quarkus-arc"},{"version":"3.17.4","group_id":"io.quarkus","artifact_id":"quarkus-rest"},{"version":"3.17.4","group_id":"io.quarkus","artifact_id":"quarkus-jdbc-mysql"},{"version":"3.17.4","group_id":"io.quarkus","artifact_id":"quarkus-rest-jackson"},{"version":"3.17.4","group_id":"io.quarkus","artifact_id":"quarkus-hibernate-orm"}]},"context":{"app":{"name":"a+44PF2KBJKRLwy0Yo8GyjTNrp3xoAKCbRHoDTEI4wc=","version":"IKIkRVwfdrYb6R79VE36wZTl81k86scX3QCOPgmfYtM="},"kubernetes":{"detected":"false"},"java":{"vendor":"Amazon.com Inc.","version":"17.0.13"},"os":{"name":"Mac OS X","os_arch":"aarch64","version":"14.6.1"},"build":{"gradle_version":"N/A","maven_version":"3.9.6"},"graalvm":{"vendor":"N/A","java_version":"N/A","version":"N/A"},"ci":{"name":"unknown"},"timezone":"Europe/Rome","quarkus":{"version":"3.17.4"},"ip":"0.0.0.0","location":{"locale_country":"IT"}},"timestamp":"2024-12-16T12:01:18.146898Z","userId":"fd53ef4e-a84c-479f-92e1-08e1ca8f4afb"}